[
  {
    "id": "karma",
    "name": "Karma",
    "region": "Ionia",
    "icon": "/assets/champions/karma.png",
    "lore": "Karma is the living embodiment of Ionia's soul...",
    "abilities": {
      "Q": "Inner Flame",
      "W": "Focused Resolve",
      "E": "Inspire",
      "R": "Mantra"
    },
    "skins": ["Traditional", "Order of the Lotus", "Dawnbringer"]
  },
  {
    "id": "garen",
    "name": "Garen",
    "region": "Demacia",
    "icon": "/assets/champions/garen.png",
    "lore": "A proud and noble warrior...",
    "abilities": {
      "Q": "Decisive Strike",
      "W": "Courage",
      "E": "Judgement",
      "R": "Demacian Justice"
    },
    "skins": ["Rugged", "Steel Legion", "God-King"]
  }
]
